whisperspeech/__init__.py
whisperspeech/a2wav.py
whisperspeech/benchmark.py
whisperspeech/extract_metrics.py
whisperspeech/extract_spk_emb.py
whisperspeech/extract_stoks.py
whisperspeech/fetch_models.py
whisperspeech/inference.py
whisperspeech/languages.py
whisperspeech/modules.py
whisperspeech/pipeline.py
whisperspeech/prepare_s2a_atoks.py
whisperspeech/prepare_t2s_txts.py
whisperspeech/s2a_delar_mup_wds_mlang.py
whisperspeech/s2a_delar_mup_wds_mlang_cond.py
whisperspeech/split_out_val_datasets.py
whisperspeech/t2s_up_wds_mlang_enclm.py
whisperspeech/testing.py
whisperspeech/train.py
whisperspeech/train_multi.py
whisperspeech/utils.py
whisperspeech/vad.py
whisperspeech/vad_merge.py
whisperspeech/vq_stoks.py
whisperspeech/wer_metrics.py
whisperspeech/wh_transcribe.py
WhisperSpeech-0.8.9.dist-info/LICENSE
WhisperSpeech-0.8.9.dist-info/METADATA
WhisperSpeech-0.8.9.dist-info/WHEEL
WhisperSpeech-0.8.9.dist-info/entry_points.txt
WhisperSpeech-0.8.9.dist-info/top_level.txt
WhisperSpeech-0.8.9.dist-info/RECORD
