Metadata-Version: 2.1
Name: WhisperSpeech
Version: 0.8.9
Summary: An Open Source text-to-speech system built by inverting Whisper
Home-page: https://github.com/collabora/WhisperSpeech
Author: Jakub Piotr Cłapa
Author-email: jpc@collabora.com
License: MIT License
Keywords: nbdev jupyter notebook python
Classifier: Development Status :: 4 - Beta
Classifier: Intended Audience :: Developers
Classifier: Natural Language :: English
Classifier: Programming Language :: Python :: 3.7
Classifier: Programming Language :: Python :: 3.8
Classifier: Programming Language :: Python :: 3.9
Classifier: Programming Language :: Python :: 3.10
Classifier: License :: OSI Approved :: MIT License
Requires-Python: >=3.7
License-File: LICENSE
Requires-Dist: vocos
Requires-Dist: speechbrain <1.0
Requires-Dist: requests
Requires-Dist: huggingface-hub
Requires-Dist: fastprogress
Requires-Dist: fastcore
Requires-Dist: torch >=2
Requires-Dist: torchaudio
Requires-Dist: soundfile
Provides-Extra: dev
Requires-Dist: vector-quantize-pytorch ==1.6.22 ; extra == 'dev'
Requires-Dist: openai-whisper ; extra == 'dev'
Requires-Dist: webdataset ; extra == 'dev'
Requires-Dist: wandb ; extra == 'dev'
Requires-Dist: whisper-normalizer ; extra == 'dev'
Requires-Dist: jiwer ; extra == 'dev'
Requires-Dist: matplotlib ; extra == 'dev'
Requires-Dist: pandas ; extra == 'dev'
Requires-Dist: pyarrow ; extra == 'dev'
Requires-Dist: scikit-learn ; extra == 'dev'
Requires-Dist: ipython ; extra == 'dev'
